aglog/__init__.py
aglog/filter/__init__.py
aglog/filter/word_filter.py
aglog/formatter/__init__.py
aglog/formatter/iso8601_formatter.py
aglog/formatter/json_formatter.py
aglog/handler/__init__.py
aglog/handler/queue_listener_handler.py
aglog/handler/slack_handler.py
aglog/handler/web_handler.py
aglog/loader/__init__.py
aglog/loader/loader.py
aglog/loader/yaml_loader.py
aglog/utils/__init__.py
aglog/utils/local_timezone.py
aglog/utils/request_backend.py
aglog/utils/retry.py
aglog/utils/time_semaphore.py
aglog-0.1.5.dist-info/METADATA
aglog-0.1.5.dist-info/WHEEL
aglog-0.1.5.dist-info/RECORD
