Metadata-Version: 2.3
Name: aglog
Version: 0.1.5
Summary: Logging support tools for python
Project-URL: Repository, https://github.com/agarichan/aglog
Author-email: agarichan <ag4r1chan@gmail.com>
License-Expression: MIT
Requires-Python: >=3.10
Requires-Dist: aiohttp>=3.9.0
Requires-Dist: pygments>=2.16.1
Requires-Dist: pyyaml>=6.0.1
Requires-Dist: typing-extensions>=4.8.0
